<?xml version="1.0" encoding="UTF-8"?>
<ale:ECReports xmlns:ale="urn:epcglobal:ale:xsd:1" xmlns:ale_mojix_ext="urn:mojix:ale:xsd:1" xmlns:epcglobal="urn:epcglobal:xsd:1" xmlns:ns3="urn:epcglobal:ale:xsd:1" xmlns:xsi="http://www.w3.org/2001/XMLSchema-instance" xsi:schemaLocation="urn:epcglobal:ale:xsd:1 http://192.168.78.13:8080/services/ALEService/?xsd=EPCglobal-ale-1_1-ale.xsd" specName="MojStoreTest" schemaVersion="1.1" terminationTrigger="urn:com.mojix.epc.triggers:duration_elapsed:MojStoreTest" creationDate="2014-09-11T16:13:20.492-07:00" totalMilliseconds="1000" terminationCondition="TRIGGER" initiationCondition="REQUESTED" ALEID="PRVSID" date="ts%" ale_mojix_ext:longitude="-0.475919" ale_mojix_ext:latitude="51.344924" ale_mojix_ext:elevation="0.0" ale_mojix_ext:declination="0.0" ale_mojix_ext:units="ft">
   <reports>
      <report reportName="MojStoreTest" ale_mojix_ext:reportID="__REPORT_ID__">
         <group>
            <groupList>
               __BODY__
            </groupList>
            <groupCount>
               <count>__COUNT__</count>
            </groupCount>
         </group>
      </report>
   </reports>
</ale:ECReports>